with_venv/__init__.py
with_venv/with_venv.py
with_venv-0.0.1.dist-info/DESCRIPTION.rst
with_venv-0.0.1.dist-info/METADATA
with_venv-0.0.1.dist-info/RECORD
with_venv-0.0.1.dist-info/WHEEL
with_venv-0.0.1.dist-info/metadata.json
with_venv-0.0.1.dist-info/top_level.txt
with_venv-0.0.1.dist-info/zip-safe
